mcp_kb/__init__.py
mcp_kb/config.py
mcp_kb/projects.py
mcp_kb/cli/__init__.py
mcp_kb/cli/args.py
mcp_kb/cli/main.py
mcp_kb/cli/reindex.py
mcp_kb/cli/runtime_config.py
mcp_kb/data/KNOWLEDBASE_DOC.md
mcp_kb/data/__init__.py
mcp_kb/ingest/__init__.py
mcp_kb/ingest/chroma.py
mcp_kb/knowledge/__init__.py
mcp_kb/knowledge/bootstrap.py
mcp_kb/knowledge/events.py
mcp_kb/knowledge/metadata.py
mcp_kb/knowledge/search.py
mcp_kb/knowledge/store.py
mcp_kb/security/__init__.py
mcp_kb/security/path_validation.py
mcp_kb/server/__init__.py
mcp_kb/server/app.py
mcp_kb/ui/__init__.py
mcp_kb/ui/api.py
mcp_kb/ui/server.py
mcp_kb/ui/assets/index.html
mcp_kb/ui/assets/assets/index.css
mcp_kb/ui/assets/entries/index.js
mcp_kb/utils/__init__.py
mcp_kb/utils/filesystem.py
mcp_kb-0.4.1.dist-info/METADATA
mcp_kb-0.4.1.dist-info/WHEEL
mcp_kb-0.4.1.dist-info/entry_points.txt
mcp_kb-0.4.1.dist-info/top_level.txt
mcp_kb-0.4.1.dist-info/RECORD
