Metadata-Version: 2.4
Name: mcp-kb
Version: 0.4.1
Summary: MCP server exposing a local markdown knowledge base
Author: LLM Maintainer
Requires-Python: >=3.11
Requires-Dist: chardet>=5.2.0
Requires-Dist: httpx>=0.28.1
Requires-Dist: mcp[cli]>=1.15.0
Requires-Dist: pydantic>=2.11.9
Provides-Extra: vector
Requires-Dist: chromadb>=1.1.0; extra == "vector"
Requires-Dist: tiktoken>=0.11.0; extra == "vector"
Requires-Dist: langchain-text-splitters>=0.3.11; extra == "vector"
Requires-Dist: umap-learn>=0.5.9.post2; extra == "vector"
Provides-Extra: vector-gpu
Requires-Dist: mcp-kb[vector]; extra == "vector-gpu"
Requires-Dist: onnxruntime-gpu; extra == "vector-gpu"
Provides-Extra: sentence-transformer
Requires-Dist: mcp-kb[vector]; extra == "sentence-transformer"
Requires-Dist: sentence-transformers>=5.1.1; extra == "sentence-transformer"
Provides-Extra: dev
Requires-Dist: pytest>=8.4.2; extra == "dev"
Requires-Dist: pytest-cov>=6.2.1; extra == "dev"
